esmcheckds2/__init__.py
esmcheckds2/console.py
esmcheckds2/esmcheckds2.py
esmcheckds2/version.py
esmcheckds2-1.0.3.dist-info/LICENSE
esmcheckds2-1.0.3.dist-info/METADATA
esmcheckds2-1.0.3.dist-info/WHEEL
esmcheckds2-1.0.3.dist-info/entry_points.txt
esmcheckds2-1.0.3.dist-info/top_level.txt
esmcheckds2-1.0.3.dist-info/RECORD
