Metadata-Version: 2.1
Name: esmcheckds2
Version: 1.0.3
Summary: McAfee ESM Data Source Reporting
Home-page: https://github.com/andywalden/esmcheckds2
Author: Andy Walden
Author-email: aw@krakencodes.com
License: ISC
Keywords: esmcheckds2
Platform: UNKNOWN
Classifier: Development Status :: 5 - Production/Stable
Classifier: Intended Audience :: Developers
Classifier: License :: OSI Approved :: ISC License (ISCL)
Classifier: Natural Language :: English
Classifier: Operating System :: MacOS
Classifier: Operating System :: Unix
Classifier: Operating System :: Microsoft :: Windows
Classifier: Programming Language :: Python :: 3.4
Classifier: Programming Language :: Python :: 3.5
Classifier: Programming Language :: Python :: 3.6
Classifier: Programming Language :: Python :: 3 :: Only
Requires-Python: >=3
Requires-Dist: requests
Requires-Dist: prettytable
Requires-Dist: python-dateutil
